PyWdxServiceAgent/BizRequest.py
PyWdxServiceAgent/BizResponse.py
PyWdxServiceAgent/BizServiceAgent.py
PyWdxServiceAgent/QueryParameterCollection.py
PyWdxServiceAgent/QueryRequest.py
PyWdxServiceAgent/QueryResponse.py
PyWdxServiceAgent/QueryServiceAgent.py
PyWdxServiceAgent/TypeEncoder.py
PyWdxServiceAgent/WdxCertServiceAgent.py
PyWdxServiceAgent/WdxComputerInfo.py
PyWdxServiceAgent/WdxUtil.py
PyWdxServiceAgent/__init__.py
PyWdxServiceAgent-0.1.17.dist-info/METADATA
PyWdxServiceAgent-0.1.17.dist-info/WHEEL
PyWdxServiceAgent-0.1.17.dist-info/top_level.txt
PyWdxServiceAgent-0.1.17.dist-info/RECORD
