Metadata-Version: 2.1
Name: PyWdxServiceAgent
Version: 0.1.17
Summary: Wdworker BackendService Agent
Home-page: https://github.com/genfeel/Wdworker
Author: genfeel
Author-email: genfeel@hotmail.com
Classifier: Programming Language :: Python :: 3
Classifier: License :: OSI Approved :: MIT License
Classifier: Operating System :: OS Independent
Requires-Python: >=3.6
